{
  "header": {
    "type": "esearch",
    "version": "0.3"
  },
  "esearchresult": {
    "count": "478",
    "retmax": "50",
    "retstart": "0",
    "idlist": [
      "42182331",
      "42161587",
      "42137389",
      "42122249",
      "42106643",
      "42063363",
      "42029414",
      "42017538",
      "33074640",
      "41942316",
      "41928196",
      "41900781",
      "41835766",
      "41734103",
      "41692080",
      "41622521",
      "41615824",
      "41590508",
      "41559559",
      "41539356",
      "41475853",
      "41440136",
      "41431308",
      "41385215",
      "41361445",
      "41352035",
      "41295274",
      "41221123",
      "41211168",
      "41158987",
      "41149778",
      "41133339",
      "41111862",
      "41012503",
      "41010482",
      "40996763",
      "31613531",
      "40913882",
      "40853095",
      "40843754",
      "40809450",
      "40754968",
      "40751583",
      "40714656",
      "40645780",
      "40636590",
      "40625625",
      "40611181",
      "40584106",
      "40463402"
    ],
    "translationset": [],
    "querytranslation": "(\"pyridoxine\"[Title/Abstract] OR \"B6\"[Title/Abstract] OR \"B-complex\"[Title/Abstract] OR \"benfotiamine\"[Title/Abstract]) AND (\"supplement*\"[Title/Abstract] OR \"dietary\"[Title/Abstract] OR \"over-the-counter\"[Title/Abstract] OR \"OTC\"[Title/Abstract]) AND (\"neuropathy\"[Title/Abstract] OR \"neurotoxicity\"[Title/Abstract] OR \"toxicity\"[Title/Abstract] OR \"adverse\"[Title/Abstract])"
  }
}